[{"updated":1490138177,"instagram":{"id":"1417356146838150813","code":"BOrdef0gR6d","date":1483182041,"display_src":"https://scontent-sjc2-1.cdninstagram.com/t51.2885-15/e35/15624895_219477241842133_3442070255113863168_n.jpg","likes":{"count":3242}},"watsonClasses":[{"class":"male child","score":0.743,"type_hierarchy":"/person/male child"},{"class":"person","score":0.896},{"class":"clown","score":0.596,"type_hierarchy":"/person/entertainer/clown"},{"class":"entertainer","score":0.597},{"class":"child","score":0.779,"type_hierarchy":"/juvenile person/child"},{"class":"juvenile person","score":0.578},{"class":"son","score":0.53,"type_hierarchy":"/person/child/son"},{"class":"alizarine red color","score":0.923},{"class":"Indian red color","score":0.686}]},{"updated":1490138177,"instagram":{"id":"1417332062691784549","code":"BOrYABtg_dl","date":1483179169,"display_src":"https://scontent-sjc2-1.cdninstagram.com/t51.2885-15/e35/15803209_236108236828851_7492275237589876736_n.jpg","likes":{"count":2594}},"watsonClasses":[{"class":"red carpet","score":0.597,"type_hierarchy":"/floor cover/rug/red carpet"},{"class":"rug","score":0.597},{"class":"floor cover","score":0.597},{"class":"schoolchild","score":0.57,"type_hierarchy":"/juvenile person/schoolchild"},{"class":"juvenile person","score":0.57},{"class":"person","score":0.738},{"class":"people","score":0.553,"type_hierarchy":"/person/people"},{"class":"sporting event","score":0.53,"type_hierarchy":"/person/sporting event"},{"class":"Indian red color","score":0.927},{"class":"alizarine red color","score":0.859}]},{"updated":1490138177,"instagram":{"id":"1417318451621493170","code":"BOrU59agXmy","date":1483177547,"display_src":"https://scontent-sjc2-1.cdninstagram.com/t51.2885-15/e35/15625286_556623694543685_6827220756057817088_n.jpg","likes":{"count":2486}},"watsonClasses":[{"class":"wheelhouse","score":0.6,"type_hierarchy":"/room/compartment/wheelhouse"},{"class":"compartment","score":0.6},{"class":"room","score":0.65},{"class":"poop deck (ship)","score":0.556,"type_hierarchy":"/platform/poop deck (ship)"},{"class":"platform","score":0.562},{"class":"satellite television","score":0.539,"type_hierarchy":"/telecommunication system/satellite television"},{"class":"television","score":0.54},{"class":"telecommunication system","score":0.54},{"class":"communication system","score":0.541},{"class":"system","score":0.541},{"class":"basketball court","score":0.539},{"class":"nursery","score":0.53,"type_hierarchy":"/bedroom/nursery"},{"class":"bedroom","score":0.53},{"class":"steel blue color","score":0.977}]},{"updated":1490138177,"instagram":{"id":"1416904120497306281","code":"BOp2spfB3qp","date":1483128155,"display_src":"https://scontent-sjc2-1.cdninstagram.com/t51.2885-15/e35/14574160_1839174679685983_3276540561963614208_n.jpg","likes":{"count":2968}},"watsonClasses":[{"class":"doorsill","score":0.733,"type_hierarchy":"/device/support/doorsill"},{"class":"support","score":0.733},{"class":"device","score":0.733},{"class":"door","score":0.612},{"class":"religion related","score":0.534,"type_hierarchy":"/person/religion related"},{"class":"person","score":0.538},{"class":"stoop","score":0.53,"type_hierarchy":"/porch/stoop"},{"class":"porch","score":0.53},{"class":"Indian red color","score":0.939},{"class":"brick red color","score":0.694}]},{"updated":1490138177,"instagram":{"id":"1416809625529275854","code":"BOphNkMBtXO","date":1483116890,"display_src":"https://scontent-sjc2-1.cdninstagram.com/t51.2885-15/e35/15802160_250427975388681_8046757727411634176_n.jpg","likes":{"count":3721}},"watsonClasses":[{"class":"waxwork","score":0.597},{"class":"Secretary of State","score":0.566,"type_hierarchy":"/person/Secretary of State"},{"class":"person","score":0.571},{"class":"telephone call","score":0.562,"type_hierarchy":"/medium/telecommunication/telephone call"},{"class":"telephone","score":0.564},{"class":"telecommunication","score":0.564},{"class":"medium","score":0.564},{"class":"hair","score":0.53},{"class":"dark red color","score":0.717},{"class":"brick red color","score":0.672}]},{"updated":1490138178,"instagram":{"id":"1416741746121302642","code":"BOpRxykBuJy","date":1483108798,"display_src":"https://scontent-sjc2-1.cdninstagram.com/t51.2885-15/e35/15624670_682362428609346_707342755298279424_n.jpg","likes":{"count":3290}},"watsonClasses":[{"class":"weatherman","score":0.675,"type_hierarchy":"/person/weatherman"},{"class":"person","score":0.833},{"class":"card player","score":0.578,"type_hierarchy":"/person/contestant/card player"},{"class":"player","score":0.578},{"class":"contestant","score":0.578},{"class":"casino dealer(croupier)","score":0.533,"type_hierarchy":"/person/casino dealer(croupier)"},{"class":"reading teacher","score":0.53,"type_hierarchy":"/person/reading teacher"},{"class":"teacher","score":0.555},{"class":"sea green color","score":0.781},{"class":"greenish blue color","score":0.544}]},{"updated":1490138178,"instagram":{"id":"1416721927858612454","code":"BOpNRZXhOjm","date":1483106436,"display_src":"https://scontent-sjc2-1.cdninstagram.com/t51.2885-15/e35/15624549_971629512969293_5660588478891556864_n.jpg","likes":{"count":2310}},"watsonClasses":[{"class":"booth","score":0.625,"type_hierarchy":"/shop/booth"},{"class":"shop","score":0.645},{"class":"drawing chalk","score":0.547},{"class":"display window","score":0.54,"type_hierarchy":"/framework/display window"},{"class":"window","score":0.545},{"class":"framework","score":0.545},{"class":"sales booth","score":0.535,"type_hierarchy":"/shop/sales booth"},{"class":"graffiti","score":0.534},{"class":"greengrocery","score":0.53,"type_hierarchy":"/marketplace/grocery store/greengrocery"},{"class":"grocery store","score":0.531},{"class":"marketplace","score":0.544},{"class":"yellow color","score":0.809},{"class":"ultramarine color","score":0.628}]},{"updated":1490138178,"instagram":{"id":"1416597580544424731","code":"BOow_56Bzsb","date":1483091612,"display_src":"https://scontent-sjc2-1.cdninstagram.com/t51.2885-15/e35/15802496_347665522287515_3606311419420606464_n.jpg","likes":{"count":3314}},"watsonClasses":[{"class":"circus acrobat","score":0.642,"type_hierarchy":"/person/contestant/athlete/circus acrobat"},{"class":"athlete","score":0.642},{"class":"contestant","score":0.642},{"class":"person","score":0.69},{"class":"juggler","score":0.536,"type_hierarchy":"/person/entertainer/juggler"},{"class":"entertainer","score":0.537},{"class":"jungle gym","score":0.535},{"class":"roller coaster","score":0.53,"type_hierarchy":"/device/roller coaster"},{"class":"device","score":0.53},{"class":"alizarine red color","score":0.829},{"class":"maroon color","score":0.762}]},{"updated":1490138178,"instagram":{"id":"1416554380169441649","code":"BOonLQbBfFx","date":1483086462,"display_src":"https://scontent-sjc2-1.cdninstagram.com/t51.2885-15/e35/15623878_378822535808498_8601396876165513216_n.jpg","likes":{"count":2120}},"watsonClasses":[{"class":"dune cycling","score":0.697,"type_hierarchy":"/sport/dune cycling"},{"class":"sport","score":0.697},{"class":"bicycle-built-for-two","score":0.546,"type_hierarchy":"/vehicle/bicycle-built-for-two"},{"class":"bicycle","score":0.606},{"class":"vehicle","score":0.736},{"class":"horse cart","score":0.53,"type_hierarchy":"/vehicle/wagon/horse cart"},{"class":"cart","score":0.563},{"class":"wagon","score":0.581},{"class":"gray color","score":0.897}]},{"updated":1490138178,"instagram":{"id":"1416146285647861839","code":"BOnKYsyB5hP","date":1483037814,"display_src":"https://scontent-sjc2-1.cdninstagram.com/t51.2885-15/e35/15623939_226136094509814_1860807757951664128_n.jpg","likes":{"count":3529}},"watsonClasses":[{"class":"portrait of a girl","score":0.623,"type_hierarchy":"/person/portrait of a girl"},{"class":"person","score":0.752},{"class":"people","score":0.565,"type_hierarchy":"/person/people"},{"class":"celebrity","score":0.53,"type_hierarchy":"/person/adult/celebrity"},{"class":"adult","score":0.534},{"class":"coal black color","score":0.955},{"class":"black color","score":0.925}]}]